intellx/__init__.py
intellx/api.py
intellx/cli.py
intellx_api-0.0.0.0.dist-info/LICENSE
intellx_api-0.0.0.0.dist-info/METADATA
intellx_api-0.0.0.0.dist-info/WHEEL
intellx_api-0.0.0.0.dist-info/entry_points.txt
intellx_api-0.0.0.0.dist-info/top_level.txt
intellx_api-0.0.0.0.dist-info/RECORD
