Metadata-Version: 2.1
Name: intellx-api
Version: 0.0.0.0
License-File: LICENSE
Requires-Dist: pyyaml
Requires-Dist: load-dotenv
